{"_default": {"1": {"name": "FloodgatesBot"}, "2": {"name": "SafestBot"}, "3": {"name": "RepostSleuthBot"}, "4": {"name": "JimmyModBot"}, "5": {"bot": "DuplicateDestroyer"}, "6": {"name": "CovenBot"}, "7": {"name": "MAGIC_EYE_BOT"}, "8": {"name": "Saferbot"}, "9": {"name": "AutoModerator"}, "10": {"name": "BotTerminator"}, "11": {"name": "CivilServantBot"}, "12": {"bot": "DuplicateDestroyer"}, "13": {"name": "BotDefense"}, "14": {"name": "I_Am_A_Real_Bot"}, "15": {"bot": "DuplicateDestroyer"}, "16": {"bot": "DuplicateDestroyer"}, "17": {"bot": "DuplicateDestroyer"}, "18": {"bot": "DuplicateDestroyer"}}}